{
    "uid": "079bfb3a-0029-473b-b8df-851aabf10333",
    "name": "27_CatBoost",
    "preprocessing": [
        {
            "remove_columns": [
                "Humidity"
            ],
            "ml_task": "binary_classification",
            "params": {
                "columns_preprocessing": {
                    "Humidity": [
                        "remove_column"
                    ]
                },
                "target_preprocessing": [
                    "na_exclude"
                ],
                "ml_task": "binary_classification"
            }
        },
        {
            "remove_columns": [
                "Humidity"
            ],
            "ml_task": "binary_classification",
            "params": {
                "columns_preprocessing": {
                    "Humidity": [
                        "remove_column"
                    ]
                },
                "target_preprocessing": [
                    "na_exclude"
                ],
                "ml_task": "binary_classification"
            }
        },
        {
            "remove_columns": [
                "Humidity"
            ],
            "ml_task": "binary_classification",
            "params": {
                "columns_preprocessing": {
                    "Humidity": [
                        "remove_column"
                    ]
                },
                "target_preprocessing": [
                    "na_exclude"
                ],
                "ml_task": "binary_classification"
            }
        },
        {
            "remove_columns": [
                "Humidity"
            ],
            "ml_task": "binary_classification",
            "params": {
                "columns_preprocessing": {
                    "Humidity": [
                        "remove_column"
                    ]
                },
                "target_preprocessing": [
                    "na_exclude"
                ],
                "ml_task": "binary_classification"
            }
        },
        {
            "remove_columns": [
                "Humidity"
            ],
            "ml_task": "binary_classification",
            "params": {
                "columns_preprocessing": {
                    "Humidity": [
                        "remove_column"
                    ]
                },
                "target_preprocessing": [
                    "na_exclude"
                ],
                "ml_task": "binary_classification"
            }
        }
    ],
    "learners": [
        {
            "library_version": "1.2.8",
            "algorithm_name": "CatBoost",
            "algorithm_short_name": "CatBoost",
            "uid": "004a81df-3a32-4509-96c0-448c83c3eabb",
            "params": {
                "model_type": "CatBoost",
                "ml_task": "binary_classification",
                "n_jobs": -1,
                "seed": 1238,
                "learning_rate": 0.2,
                "depth": 8,
                "rsm": 0.9,
                "loss_function": "Logloss",
                "eval_metric": "Logloss",
                "explain_level": 1
            },
            "name": "learner_fold_0",
            "best_ntree_limit": 21
        },
        {
            "library_version": "1.2.8",
            "algorithm_name": "CatBoost",
            "algorithm_short_name": "CatBoost",
            "uid": "b7a7203e-f509-4ca7-a409-0f2f67e8b903",
            "params": {
                "model_type": "CatBoost",
                "ml_task": "binary_classification",
                "n_jobs": -1,
                "seed": 1238,
                "learning_rate": 0.2,
                "depth": 8,
                "rsm": 0.9,
                "loss_function": "Logloss",
                "eval_metric": "Logloss",
                "explain_level": 1
            },
            "name": "learner_fold_1",
            "best_ntree_limit": 8
        },
        {
            "library_version": "1.2.8",
            "algorithm_name": "CatBoost",
            "algorithm_short_name": "CatBoost",
            "uid": "9e59f113-1a5e-49d1-b927-15ba2823e65b",
            "params": {
                "model_type": "CatBoost",
                "ml_task": "binary_classification",
                "n_jobs": -1,
                "seed": 1238,
                "learning_rate": 0.2,
                "depth": 8,
                "rsm": 0.9,
                "loss_function": "Logloss",
                "eval_metric": "Logloss",
                "explain_level": 1
            },
            "name": "learner_fold_2",
            "best_ntree_limit": 61
        },
        {
            "library_version": "1.2.8",
            "algorithm_name": "CatBoost",
            "algorithm_short_name": "CatBoost",
            "uid": "ad82c7db-301e-407b-860c-9e0ecdc70bce",
            "params": {
                "model_type": "CatBoost",
                "ml_task": "binary_classification",
                "n_jobs": -1,
                "seed": 1238,
                "learning_rate": 0.2,
                "depth": 8,
                "rsm": 0.9,
                "loss_function": "Logloss",
                "eval_metric": "Logloss",
                "explain_level": 1
            },
            "name": "learner_fold_3",
            "best_ntree_limit": 90
        },
        {
            "library_version": "1.2.8",
            "algorithm_name": "CatBoost",
            "algorithm_short_name": "CatBoost",
            "uid": "247380e6-1469-46ef-a3ef-b647d1ada61c",
            "params": {
                "model_type": "CatBoost",
                "ml_task": "binary_classification",
                "n_jobs": -1,
                "seed": 1238,
                "learning_rate": 0.2,
                "depth": 8,
                "rsm": 0.9,
                "loss_function": "Logloss",
                "eval_metric": "Logloss",
                "explain_level": 1
            },
            "name": "learner_fold_4",
            "best_ntree_limit": 12
        }
    ],
    "params": {
        "additional": {
            "max_rounds": 10000,
            "early_stopping_rounds": 50,
            "max_rows_limit": null,
            "max_cols_limit": null
        },
        "preprocessing": {
            "columns_preprocessing": {
                "Humidity": [
                    "remove_column"
                ]
            },
            "target_preprocessing": [
                "na_exclude"
            ],
            "ml_task": "binary_classification"
        },
        "validation_strategy": {
            "validation_type": "kfold",
            "k_folds": 5,
            "shuffle": true,
            "stratify": true,
            "X_path": "results\\42ee5dfa-3be3-4c90-8069-2e1c557a77e2\\X.data",
            "y_path": "results\\42ee5dfa-3be3-4c90-8069-2e1c557a77e2\\y.data",
            "results_path": "results\\42ee5dfa-3be3-4c90-8069-2e1c557a77e2"
        },
        "learner": {
            "model_type": "CatBoost",
            "ml_task": "binary_classification",
            "n_jobs": -1,
            "seed": 1238,
            "learning_rate": 0.2,
            "depth": 8,
            "rsm": 0.9,
            "loss_function": "Logloss",
            "eval_metric": "Logloss",
            "explain_level": 1
        },
        "automl_random_state": 1234,
        "ml_task": "binary_classification",
        "explain_level": 1,
        "name": "27_CatBoost",
        "status": "initialized",
        "final_loss": null,
        "train_time": null,
        "data_type": "original",
        "max_time_for_learner": 72.0
    },
    "saved": [
        "27_CatBoost\\learner_fold_0.catboost",
        "27_CatBoost\\learner_fold_1.catboost",
        "27_CatBoost\\learner_fold_2.catboost",
        "27_CatBoost\\learner_fold_3.catboost",
        "27_CatBoost\\learner_fold_4.catboost"
    ],
    "predictions_fname": "27_CatBoost\\predictions_out_of_folds.csv",
    "metric_name": "logloss",
    "final_loss": "0.5813426448206485",
    "train_time": 39.154825925827026,
    "is_stacked": false,
    "joblib_version": "1.5.2",
    "threshold": 0.7370039947147908,
    "single_prediction_time": 0.02944779396057129
}